usdb_syncer/__init__.py
usdb_syncer/_version.py
usdb_syncer/addons.py
usdb_syncer/constants.py
usdb_syncer/custom_data.py
usdb_syncer/discord.py
usdb_syncer/download_options.py
usdb_syncer/errors.py
usdb_syncer/events.py
usdb_syncer/hooks.py
usdb_syncer/json_export.py
usdb_syncer/logger.py
usdb_syncer/media_player.py
usdb_syncer/meta_tags.py
usdb_syncer/path_template.py
usdb_syncer/postprocessing.py
usdb_syncer/remote_config.py
usdb_syncer/resource_dl.py
usdb_syncer/settings.py
usdb_syncer/song_loader.py
usdb_syncer/song_routines.py
usdb_syncer/sync_meta.py
usdb_syncer/usdb_id_file.py
usdb_syncer/usdb_scraper.py
usdb_syncer/usdb_song.py
usdb_syncer/utils.py
usdb_syncer/data/.gitignore
usdb_syncer/data/__init__.py
usdb_syncer/db/__init__.py
usdb_syncer/db/sql/1_migration.sql
usdb_syncer/db/sql/2_migration.sql
usdb_syncer/db/sql/3_migration.sql
usdb_syncer/db/sql/4_migration.sql
usdb_syncer/db/sql/5_migration.sql
usdb_syncer/db/sql/6_migration.sql
usdb_syncer/db/sql/7_migration.sql
usdb_syncer/db/sql/8_migration.sql
usdb_syncer/db/sql/9_migration.sql
usdb_syncer/db/sql/__init__.py
usdb_syncer/db/sql/insert_active_sync_meta.sql
usdb_syncer/db/sql/insert_active_sync_metas.sql
usdb_syncer/db/sql/select_song_id.sql
usdb_syncer/db/sql/select_sync_meta.sql
usdb_syncer/db/sql/select_unique_search_name.sql
usdb_syncer/db/sql/select_usdb_song.sql
usdb_syncer/db/sql/setup_session_script.sql
usdb_syncer/db/sql/upsert_custom_meta_data.sql
usdb_syncer/db/sql/upsert_resource.sql
usdb_syncer/db/sql/upsert_sync_meta.sql
usdb_syncer/db/sql/upsert_usdb_song.sql
usdb_syncer/db/sql/upsert_usdb_song_playing.sql
usdb_syncer/db/sql/upsert_usdb_song_status.sql
usdb_syncer/gui/__init__.py
usdb_syncer/gui/about_dialog.py
usdb_syncer/gui/comment_dialog.py
usdb_syncer/gui/cover_widget.py
usdb_syncer/gui/custom_data_dialog.py
usdb_syncer/gui/debug_console.py
usdb_syncer/gui/events.py
usdb_syncer/gui/external_deps_dialog.py
usdb_syncer/gui/fonts.py
usdb_syncer/gui/gui_utils.py
usdb_syncer-0.20.0.dist-info/METADATA
usdb_syncer-0.20.0.dist-info/WHEEL
usdb_syncer-0.20.0.dist-info/entry_points.txt
usdb_syncer-0.20.0.dist-info/licenses/LICENSE
usdb_syncer-0.20.0.dist-info/licenses/NOTICE.txt
usdb_syncer-0.20.0.dist-info/licenses/licenses/LICENSE.APACHE
usdb_syncer-0.20.0.dist-info/licenses/licenses/LICENSE.CCBY3
usdb_syncer-0.20.0.dist-info/licenses/licenses/LICENSE.GPL2
usdb_syncer-0.20.0.dist-info/licenses/licenses/LICENSE.GPL3
usdb_syncer-0.20.0.dist-info/licenses/licenses/LICENSE.MPL2
usdb_syncer-0.20.0.dist-info/RECORD
