Metadata-Version: 2.4
Name: usdb_syncer
Version: 0.20.0
Summary: A download manager for USDB songs.
Project-URL: Repository, https://github.com/bohning/usdb_syncer
Author-email: Markus Böhning <markus.boehning@gmail.com>
License-Expression: GPL-3.0-only
License-File: LICENSE
License-File: NOTICE.txt
License-File: licenses/LICENSE.APACHE
License-File: licenses/LICENSE.CCBY3
License-File: licenses/LICENSE.GPL2
License-File: licenses/LICENSE.GPL3
License-File: licenses/LICENSE.MPL2
Requires-Python: <3.15,>=3.11
Requires-Dist: attrs
Requires-Dist: beautifulsoup4
Requires-Dist: diff-match-patch
Requires-Dist: ffmpeg-normalize>=1.27
Requires-Dist: filetype
Requires-Dist: flask<4,>=3.1.1
Requires-Dist: keyring
Requires-Dist: lxml
Requires-Dist: mutagen
Requires-Dist: numpy<3,>=2.2.5
Requires-Dist: packaging
Requires-Dist: pillow>=10
Requires-Dist: platformdirs
Requires-Dist: pyside6
Requires-Dist: qrcode[pil]~=8.2
Requires-Dist: reportlab
Requires-Dist: requests
Requires-Dist: send2trash
Requires-Dist: sounddevice<0.6,>=0.5.1
Requires-Dist: soundfile<0.14,>=0.13.1
Requires-Dist: unidecode
Requires-Dist: yt-dlp[curl-cffi,default]
